CHANGELOG.txt
LICENCE.txt
MANIFEST.in
README.txt
setup.py
huffman_file_compression/__init__.py
huffman_file_compression.egg-info/PKG-INFO
huffman_file_compression.egg-info/SOURCES.txt
huffman_file_compression.egg-info/dependency_links.txt
huffman_file_compression.egg-info/top_level.txt